minibot/__init__.py
minibot/msgraph.py
minibot/sharepoint.py
minibot-0.1.0.dist-info/METADATA
minibot-0.1.0.dist-info/WHEEL
minibot-0.1.0.dist-info/top_level.txt
minibot-0.1.0.dist-info/RECORD
