Metadata-Version: 2.4
Name: minibot
Version: 0.1.0
Summary: Librería de utilerías para automatizaciones RPA con Microsoft Graph y otras herramientas.
Author: Raul Sanz
Author-email: mail@rulosanz.com
Classifier: Programming Language :: Python :: 3
Classifier: Operating System :: OS Independent
Requires-Python: >=3.12
Requires-Dist: msal>=1.0.0
Requires-Dist: requests>=2.0.0
Requires-Dist: python-dotenv>=1.0.0
Requires-Dist: pandas>=1.0.0
Requires-Dist: openpyxl>=3.0.0
Dynamic: author
Dynamic: author-email
Dynamic: classifier
Dynamic: requires-dist
Dynamic: requires-python
Dynamic: summary
